{"nodes": [{"id": "d_jamproject_expensetracker_backend_tests_expensetracker_unittests_auth_authservicetests_cs", "label": "AuthServiceTests.cs", "file_type": "code", "source_file": "backend/tests/ExpenseTracker.UnitTests/Auth/AuthServiceTests.cs", "source_location": "L1"}, {"id": "auth_authservicetests_authservicetests", "label": "AuthServiceTests", "file_type": "code", "source_file": "backend/tests/ExpenseTracker.UnitTests/Auth/AuthServiceTests.cs", "source_location": "L12"}, {"id": "iuserrepository", "label": "IUserRepository", "file_type": "code", "source_file": "", "source_location": ""}, {"id": "ipasswordhasher", "label": "IPasswordHasher", "file_type": "code", "source_file": "", "source_location": ""}, {"id": "ijwttokenservice", "label": "IJwtTokenService", "file_type": "code", "source_file": "", "source_location": ""}, {"id": "irefreshtokenservice", "label": "IRefreshTokenService", "file_type": "code", "source_file": "", "source_location": ""}, {"id": "authservice", "label": "AuthService", "file_type": "code", "source_file": "", "source_location": ""}, {"id": "guid", "label": "Guid", "file_type": "code", "source_file": "", "source_location": ""}, {"id": "string", "label": "string", "file_type": "code", "source_file": "", "source_location": ""}, {"id": "datetimeoffset", "label": "DateTimeOffset", "file_type": "code", "source_file": "", "source_location": ""}, {"id": "auth_authservicetests_authservicetests_createrefreshtoken", "label": ".CreateRefreshToken()", "file_type": "code", "source_file": "backend/tests/ExpenseTracker.UnitTests/Auth/AuthServiceTests.cs", "source_location": "L29"}, {"id": "refreshtoken", "label": "RefreshToken", "file_type": "code", "source_file": "", "source_location": ""}, {"id": "auth_authservicetests_authservicetests_register_creates_user_and_returns_tokens", "label": ".Register_creates_user_and_returns_tokens()", "file_type": "code", "source_file": "backend/tests/ExpenseTracker.UnitTests/Auth/AuthServiceTests.cs", "source_location": "L39"}, {"id": "task", "label": "Task", "file_type": "code", "source_file": "", "source_location": ""}, {"id": "fact", "label": "Fact", "file_type": "code", "source_file": "", "source_location": ""}, {"id": "trait", "label": "Trait", "file_type": "code", "source_file": "", "source_location": ""}, {"id": "auth_authservicetests_authservicetests_register_rejects_duplicate_email", "label": ".Register_rejects_duplicate_email()", "file_type": "code", "source_file": "backend/tests/ExpenseTracker.UnitTests/Auth/AuthServiceTests.cs", "source_location": "L68"}, {"id": "auth_authservicetests_authservicetests_login_with_correct_password_returns_tokens", "label": ".Login_with_correct_password_returns_tokens()", "file_type": "code", "source_file": "backend/tests/ExpenseTracker.UnitTests/Auth/AuthServiceTests.cs", "source_location": "L86"}, {"id": "auth_authservicetests_authservicetests_login_with_wrong_password_throws_invalidcredentials", "label": ".Login_with_wrong_password_throws_InvalidCredentials()", "file_type": "code", "source_file": "backend/tests/ExpenseTracker.UnitTests/Auth/AuthServiceTests.cs", "source_location": "L110"}, {"id": "auth_authservicetests_authservicetests_login_with_nonexistent_email_throws_invalidcredentials", "label": ".Login_with_nonexistent_email_throws_InvalidCredentials()", "file_type": "code", "source_file": "backend/tests/ExpenseTracker.UnitTests/Auth/AuthServiceTests.cs", "source_location": "L127"}, {"id": "auth_authservicetests_authservicetests_refresh_rotates_token_and_revokes_old", "label": ".Refresh_rotates_token_and_revokes_old()", "file_type": "code", "source_file": "backend/tests/ExpenseTracker.UnitTests/Auth/AuthServiceTests.cs", "source_location": "L143"}, {"id": "auth_authservicetests_authservicetests_refresh_with_revoked_token_throws", "label": ".Refresh_with_revoked_token_throws()", "file_type": "code", "source_file": "backend/tests/ExpenseTracker.UnitTests/Auth/AuthServiceTests.cs", "source_location": "L167"}, {"id": "auth_authservicetests_authservicetests_refresh_with_expired_token_throws", "label": ".Refresh_with_expired_token_throws()", "file_type": "code", "source_file": "backend/tests/ExpenseTracker.UnitTests/Auth/AuthServiceTests.cs", "source_location": "L181"}, {"id": "auth_authservicetests_authservicetests_logout_revokes_token", "label": ".Logout_revokes_token()", "file_type": "code", "source_file": "backend/tests/ExpenseTracker.UnitTests/Auth/AuthServiceTests.cs", "source_location": "L197"}, {"id": "auth_authservicetests_authservicetests_logout_with_invalid_token_throws", "label": ".Logout_with_invalid_token_throws()", "file_type": "code", "source_file": "backend/tests/ExpenseTracker.UnitTests/Auth/AuthServiceTests.cs", "source_location": "L212"}, {"id": "auth_authservicetests_authservicetests_getme_returns_user_dto", "label": ".GetMe_returns_user_dto()", "file_type": "code", "source_file": "backend/tests/ExpenseTracker.UnitTests/Auth/AuthServiceTests.cs", "source_location": "L227"}, {"id": "auth_authservicetests_authservicetests_getme_with_nonexistent_user_throws_notfound", "label": ".GetMe_with_nonexistent_user_throws_NotFound()", "file_type": "code", "source_file": "backend/tests/ExpenseTracker.UnitTests/Auth/AuthServiceTests.cs", "source_location": "L245"}], "edges": [{"source": "d_jamproject_expensetracker_backend_tests_expensetracker_unittests_auth_authservicetests_cs", "target": "abstractions", "relation": "imports", "context": "import", "confidence": "EXTRACTED", "source_file": "backend/tests/ExpenseTracker.UnitTests/Auth/AuthServiceTests.cs", "source_location": "L1", "weight": 1.0}, {"source": "d_jamproject_expensetracker_backend_tests_expensetracker_unittests_auth_authservicetests_cs", "target": "auth", "relation": "imports", "context": "import", "confidence": "EXTRACTED", "source_file": "backend/tests/ExpenseTracker.UnitTests/Auth/AuthServiceTests.cs", "source_location": "L2", "weight": 1.0}, {"source": "d_jamproject_expensetracker_backend_tests_expensetracker_unittests_auth_authservicetests_cs", "target": "dtos", "relation": "imports", "context": "import", "confidence": "EXTRACTED", "source_file": "backend/tests/ExpenseTracker.UnitTests/Auth/AuthServiceTests.cs", "source_location": "L3", "weight": 1.0}, {"source": "d_jamproject_expensetracker_backend_tests_expensetracker_unittests_auth_authservicetests_cs", "target": "entities", "relation": "imports", "context": "import", "confidence": "EXTRACTED", "source_file": "backend/tests/ExpenseTracker.UnitTests/Auth/AuthServiceTests.cs", "source_location": "L4", "weight": 1.0}, {"source": "d_jamproject_expensetracker_backend_tests_expensetracker_unittests_auth_authservicetests_cs", "target": "exceptions", "relation": "imports", "context": "import", "confidence": "EXTRACTED", "source_file": "backend/tests/ExpenseTracker.UnitTests/Auth/AuthServiceTests.cs", "source_location": "L5", "weight": 1.0}, {"source": "d_jamproject_expensetracker_backend_tests_expensetracker_unittests_auth_authservicetests_cs", "target": "fluentassertions", "relation": "imports", "context": "import", "confidence": "EXTRACTED", "source_file": "backend/tests/ExpenseTracker.UnitTests/Auth/AuthServiceTests.cs", "source_location": "L6", "weight": 1.0}, {"source": "d_jamproject_expensetracker_backend_tests_expensetracker_unittests_auth_authservicetests_cs", "target": "nsubstitute", "relation": "imports", "context": "import", "confidence": "EXTRACTED", "source_file": "backend/tests/ExpenseTracker.UnitTests/Auth/AuthServiceTests.cs", "source_location": "L7", "weight": 1.0}, {"source": "d_jamproject_expensetracker_backend_tests_expensetracker_unittests_auth_authservicetests_cs", "target": "exceptionextensions", "relation": "imports", "context": "import", "confidence": "EXTRACTED", "source_file": "backend/tests/ExpenseTracker.UnitTests/Auth/AuthServiceTests.cs", "source_location": "L8", "weight": 1.0}, {"source": "d_jamproject_expensetracker_backend_tests_expensetracker_unittests_auth_authservicetests_cs", "target": "auth_authservicetests_authservicetests", "relation": "contains", "confidence": "EXTRACTED", "source_file": "backend/tests/ExpenseTracker.UnitTests/Auth/AuthServiceTests.cs", "source_location": "L12", "weight": 1.0}, {"source": "auth_authservicetests_authservicetests", "target": "iuserrepository", "relation": "references", "confidence": "EXTRACTED", "source_file": "backend/tests/ExpenseTracker.UnitTests/Auth/AuthServiceTests.cs", "source_location": "L14", "weight": 1.0, "context": "field"}, {"source": "auth_authservicetests_authservicetests", "target": "ipasswordhasher", "relation": "references", "confidence": "EXTRACTED", "source_file": "backend/tests/ExpenseTracker.UnitTests/Auth/AuthServiceTests.cs", "source_location": "L15", "weight": 1.0, "context": "field"}, {"source": "auth_authservicetests_authservicetests", "target": "ijwttokenservice", "relation": "references", "confidence": "EXTRACTED", "source_file": "backend/tests/ExpenseTracker.UnitTests/Auth/AuthServiceTests.cs", "source_location": "L16", "weight": 1.0, "context": "field"}, {"source": "auth_authservicetests_authservicetests", "target": "irefreshtokenservice", "relation": "references", "confidence": "EXTRACTED", "source_file": "backend/tests/ExpenseTracker.UnitTests/Auth/AuthServiceTests.cs", "source_location": "L17", "weight": 1.0, "context": "field"}, {"source": "auth_authservicetests_authservicetests", "target": "authservice", "relation": "references", "confidence": "EXTRACTED", "source_file": "backend/tests/ExpenseTracker.UnitTests/Auth/AuthServiceTests.cs", "source_location": "L18", "weight": 1.0, "context": "field"}, {"source": "auth_authservicetests_authservicetests", "target": "guid", "relation": "references", "confidence": "EXTRACTED", "source_file": "backend/tests/ExpenseTracker.UnitTests/Auth/AuthServiceTests.cs", "source_location": "L20", "weight": 1.0, "context": "field"}, {"source": "auth_authservicetests_authservicetests", "target": "string", "relation": "references", "confidence": "EXTRACTED", "source_file": "backend/tests/ExpenseTracker.UnitTests/Auth/AuthServiceTests.cs", "source_location": "L21", "weight": 1.0, "context": "field"}, {"source": "auth_authservicetests_authservicetests", "target": "datetimeoffset", "relation": "references", "confidence": "EXTRACTED", "source_file": "backend/tests/ExpenseTracker.UnitTests/Auth/AuthServiceTests.cs", "source_location": "L22", "weight": 1.0, "context": "field"}, {"source": "auth_authservicetests_authservicetests", "target": "auth_authservicetests_authservicetests_createrefreshtoken", "relation": "method", "confidence": "EXTRACTED", "source_file": "backend/tests/ExpenseTracker.UnitTests/Auth/AuthServiceTests.cs", "source_location": "L29", "weight": 1.0}, {"source": "auth_authservicetests_authservicetests_createrefreshtoken", "target": "guid", "relation": "references", "confidence": "EXTRACTED", "source_file": "backend/tests/ExpenseTracker.UnitTests/Auth/AuthServiceTests.cs", "source_location": "L29", "weight": 1.0, "context": "parameter_type"}, {"source": "auth_authservicetests_authservicetests_createrefreshtoken", "target": "datetimeoffset", "relation": "references", "confidence": "EXTRACTED", "source_file": "backend/tests/ExpenseTracker.UnitTests/Auth/AuthServiceTests.cs", "source_location": "L29", "weight": 1.0, "context": "parameter_type"}, {"source": "auth_authservicetests_authservicetests_createrefreshtoken", "target": "refreshtoken", "relation": "references", "confidence": "EXTRACTED", "source_file": "backend/tests/ExpenseTracker.UnitTests/Auth/AuthServiceTests.cs", "source_location": "L29", "weight": 1.0, "context": "return_type"}, {"source": "auth_authservicetests_authservicetests", "target": "auth_authservicetests_authservicetests_register_creates_user_and_returns_tokens", "relation": "method", "confidence": "EXTRACTED", "source_file": "backend/tests/ExpenseTracker.UnitTests/Auth/AuthServiceTests.cs", "source_location": "L39", "weight": 1.0}, {"source": "auth_authservicetests_authservicetests_register_creates_user_and_returns_tokens", "target": "task", "relation": "references", "confidence": "EXTRACTED", "source_file": "backend/tests/ExpenseTracker.UnitTests/Auth/AuthServiceTests.cs", "source_location": "L39", "weight": 1.0, "context": "return_type"}, {"source": "auth_authservicetests_authservicetests_register_creates_user_and_returns_tokens", "target": "fact", "relation": "references", "confidence": "EXTRACTED", "source_file": "backend/tests/ExpenseTracker.UnitTests/Auth/AuthServiceTests.cs", "source_location": "L39", "weight": 1.0, "context": "attribute"}, {"source": "auth_authservicetests_authservicetests_register_creates_user_and_returns_tokens", "target": "trait", "relation": "references", "confidence": "EXTRACTED", "source_file": "backend/tests/ExpenseTracker.UnitTests/Auth/AuthServiceTests.cs", "source_location": "L39", "weight": 1.0, "context": "attribute"}, {"source": "auth_authservicetests_authservicetests", "target": "auth_authservicetests_authservicetests_register_rejects_duplicate_email", "relation": "method", "confidence": "EXTRACTED", "source_file": "backend/tests/ExpenseTracker.UnitTests/Auth/AuthServiceTests.cs", "source_location": "L68", "weight": 1.0}, {"source": "auth_authservicetests_authservicetests_register_rejects_duplicate_email", "target": "task", "relation": "references", "confidence": "EXTRACTED", "source_file": "backend/tests/ExpenseTracker.UnitTests/Auth/AuthServiceTests.cs", "source_location": "L68", "weight": 1.0, "context": "return_type"}, {"source": "auth_authservicetests_authservicetests_register_rejects_duplicate_email", "target": "fact", "relation": "references", "confidence": "EXTRACTED", "source_file": "backend/tests/ExpenseTracker.UnitTests/Auth/AuthServiceTests.cs", "source_location": "L68", "weight": 1.0, "context": "attribute"}, {"source": "auth_authservicetests_authservicetests_register_rejects_duplicate_email", "target": "trait", "relation": "references", "confidence": "EXTRACTED", "source_file": "backend/tests/ExpenseTracker.UnitTests/Auth/AuthServiceTests.cs", "source_location": "L68", "weight": 1.0, "context": "attribute"}, {"source": "auth_authservicetests_authservicetests", "target": "auth_authservicetests_authservicetests_login_with_correct_password_returns_tokens", "relation": "method", "confidence": "EXTRACTED", "source_file": "backend/tests/ExpenseTracker.UnitTests/Auth/AuthServiceTests.cs", "source_location": "L86", "weight": 1.0}, {"source": "auth_authservicetests_authservicetests_login_with_correct_password_returns_tokens", "target": "task", "relation": "references", "confidence": "EXTRACTED", "source_file": "backend/tests/ExpenseTracker.UnitTests/Auth/AuthServiceTests.cs", "source_location": "L86", "weight": 1.0, "context": "return_type"}, {"source": "auth_authservicetests_authservicetests_login_with_correct_password_returns_tokens", "target": "fact", "relation": "references", "confidence": "EXTRACTED", "source_file": "backend/tests/ExpenseTracker.UnitTests/Auth/AuthServiceTests.cs", "source_location": "L86", "weight": 1.0, "context": "attribute"}, {"source": "auth_authservicetests_authservicetests_login_with_correct_password_returns_tokens", "target": "trait", "relation": "references", "confidence": "EXTRACTED", "source_file": "backend/tests/ExpenseTracker.UnitTests/Auth/AuthServiceTests.cs", "source_location": "L86", "weight": 1.0, "context": "attribute"}, {"source": "auth_authservicetests_authservicetests", "target": "auth_authservicetests_authservicetests_login_with_wrong_password_throws_invalidcredentials", "relation": "method", "confidence": "EXTRACTED", "source_file": "backend/tests/ExpenseTracker.UnitTests/Auth/AuthServiceTests.cs", "source_location": "L110", "weight": 1.0}, {"source": "auth_authservicetests_authservicetests_login_with_wrong_password_throws_invalidcredentials", "target": "task", "relation": "references", "confidence": "EXTRACTED", "source_file": "backend/tests/ExpenseTracker.UnitTests/Auth/AuthServiceTests.cs", "source_location": "L110", "weight": 1.0, "context": "return_type"}, {"source": "auth_authservicetests_authservicetests_login_with_wrong_password_throws_invalidcredentials", "target": "fact", "relation": "references", "confidence": "EXTRACTED", "source_file": "backend/tests/ExpenseTracker.UnitTests/Auth/AuthServiceTests.cs", "source_location": "L110", "weight": 1.0, "context": "attribute"}, {"source": "auth_authservicetests_authservicetests_login_with_wrong_password_throws_invalidcredentials", "target": "trait", "relation": "references", "confidence": "EXTRACTED", "source_file": "backend/tests/ExpenseTracker.UnitTests/Auth/AuthServiceTests.cs", "source_location": "L110", "weight": 1.0, "context": "attribute"}, {"source": "auth_authservicetests_authservicetests", "target": "auth_authservicetests_authservicetests_login_with_nonexistent_email_throws_invalidcredentials", "relation": "method", "confidence": "EXTRACTED", "source_file": "backend/tests/ExpenseTracker.UnitTests/Auth/AuthServiceTests.cs", "source_location": "L127", "weight": 1.0}, {"source": "auth_authservicetests_authservicetests_login_with_nonexistent_email_throws_invalidcredentials", "target": "task", "relation": "references", "confidence": "EXTRACTED", "source_file": "backend/tests/ExpenseTracker.UnitTests/Auth/AuthServiceTests.cs", "source_location": "L127", "weight": 1.0, "context": "return_type"}, {"source": "auth_authservicetests_authservicetests_login_with_nonexistent_email_throws_invalidcredentials", "target": "fact", "relation": "references", "confidence": "EXTRACTED", "source_file": "backend/tests/ExpenseTracker.UnitTests/Auth/AuthServiceTests.cs", "source_location": "L127", "weight": 1.0, "context": "attribute"}, {"source": "auth_authservicetests_authservicetests_login_with_nonexistent_email_throws_invalidcredentials", "target": "trait", "relation": "references", "confidence": "EXTRACTED", "source_file": "backend/tests/ExpenseTracker.UnitTests/Auth/AuthServiceTests.cs", "source_location": "L127", "weight": 1.0, "context": "attribute"}, {"source": "auth_authservicetests_authservicetests", "target": "auth_authservicetests_authservicetests_refresh_rotates_token_and_revokes_old", "relation": "method", "confidence": "EXTRACTED", "source_file": "backend/tests/ExpenseTracker.UnitTests/Auth/AuthServiceTests.cs", "source_location": "L143", "weight": 1.0}, {"source": "auth_authservicetests_authservicetests_refresh_rotates_token_and_revokes_old", "target": "task", "relation": "references", "confidence": "EXTRACTED", "source_file": "backend/tests/ExpenseTracker.UnitTests/Auth/AuthServiceTests.cs", "source_location": "L143", "weight": 1.0, "context": "return_type"}, {"source": "auth_authservicetests_authservicetests_refresh_rotates_token_and_revokes_old", "target": "fact", "relation": "references", "confidence": "EXTRACTED", "source_file": "backend/tests/ExpenseTracker.UnitTests/Auth/AuthServiceTests.cs", "source_location": "L143", "weight": 1.0, "context": "attribute"}, {"source": "auth_authservicetests_authservicetests_refresh_rotates_token_and_revokes_old", "target": "trait", "relation": "references", "confidence": "EXTRACTED", "source_file": "backend/tests/ExpenseTracker.UnitTests/Auth/AuthServiceTests.cs", "source_location": "L143", "weight": 1.0, "context": "attribute"}, {"source": "auth_authservicetests_authservicetests", "target": "auth_authservicetests_authservicetests_refresh_with_revoked_token_throws", "relation": "method", "confidence": "EXTRACTED", "source_file": "backend/tests/ExpenseTracker.UnitTests/Auth/AuthServiceTests.cs", "source_location": "L167", "weight": 1.0}, {"source": "auth_authservicetests_authservicetests_refresh_with_revoked_token_throws", "target": "task", "relation": "references", "confidence": "EXTRACTED", "source_file": "backend/tests/ExpenseTracker.UnitTests/Auth/AuthServiceTests.cs", "source_location": "L167", "weight": 1.0, "context": "return_type"}, {"source": "auth_authservicetests_authservicetests_refresh_with_revoked_token_throws", "target": "fact", "relation": "references", "confidence": "EXTRACTED", "source_file": "backend/tests/ExpenseTracker.UnitTests/Auth/AuthServiceTests.cs", "source_location": "L167", "weight": 1.0, "context": "attribute"}, {"source": "auth_authservicetests_authservicetests_refresh_with_revoked_token_throws", "target": "trait", "relation": "references", "confidence": "EXTRACTED", "source_file": "backend/tests/ExpenseTracker.UnitTests/Auth/AuthServiceTests.cs", "source_location": "L167", "weight": 1.0, "context": "attribute"}, {"source": "auth_authservicetests_authservicetests", "target": "auth_authservicetests_authservicetests_refresh_with_expired_token_throws", "relation": "method", "confidence": "EXTRACTED", "source_file": "backend/tests/ExpenseTracker.UnitTests/Auth/AuthServiceTests.cs", "source_location": "L181", "weight": 1.0}, {"source": "auth_authservicetests_authservicetests_refresh_with_expired_token_throws", "target": "task", "relation": "references", "confidence": "EXTRACTED", "source_file": "backend/tests/ExpenseTracker.UnitTests/Auth/AuthServiceTests.cs", "source_location": "L181", "weight": 1.0, "context": "return_type"}, {"source": "auth_authservicetests_authservicetests_refresh_with_expired_token_throws", "target": "fact", "relation": "references", "confidence": "EXTRACTED", "source_file": "backend/tests/ExpenseTracker.UnitTests/Auth/AuthServiceTests.cs", "source_location": "L181", "weight": 1.0, "context": "attribute"}, {"source": "auth_authservicetests_authservicetests_refresh_with_expired_token_throws", "target": "trait", "relation": "references", "confidence": "EXTRACTED", "source_file": "backend/tests/ExpenseTracker.UnitTests/Auth/AuthServiceTests.cs", "source_location": "L181", "weight": 1.0, "context": "attribute"}, {"source": "auth_authservicetests_authservicetests", "target": "auth_authservicetests_authservicetests_logout_revokes_token", "relation": "method", "confidence": "EXTRACTED", "source_file": "backend/tests/ExpenseTracker.UnitTests/Auth/AuthServiceTests.cs", "source_location": "L197", "weight": 1.0}, {"source": "auth_authservicetests_authservicetests_logout_revokes_token", "target": "task", "relation": "references", "confidence": "EXTRACTED", "source_file": "backend/tests/ExpenseTracker.UnitTests/Auth/AuthServiceTests.cs", "source_location": "L197", "weight": 1.0, "context": "return_type"}, {"source": "auth_authservicetests_authservicetests_logout_revokes_token", "target": "fact", "relation": "references", "confidence": "EXTRACTED", "source_file": "backend/tests/ExpenseTracker.UnitTests/Auth/AuthServiceTests.cs", "source_location": "L197", "weight": 1.0, "context": "attribute"}, {"source": "auth_authservicetests_authservicetests_logout_revokes_token", "target": "trait", "relation": "references", "confidence": "EXTRACTED", "source_file": "backend/tests/ExpenseTracker.UnitTests/Auth/AuthServiceTests.cs", "source_location": "L197", "weight": 1.0, "context": "attribute"}, {"source": "auth_authservicetests_authservicetests", "target": "auth_authservicetests_authservicetests_logout_with_invalid_token_throws", "relation": "method", "confidence": "EXTRACTED", "source_file": "backend/tests/ExpenseTracker.UnitTests/Auth/AuthServiceTests.cs", "source_location": "L212", "weight": 1.0}, {"source": "auth_authservicetests_authservicetests_logout_with_invalid_token_throws", "target": "task", "relation": "references", "confidence": "EXTRACTED", "source_file": "backend/tests/ExpenseTracker.UnitTests/Auth/AuthServiceTests.cs", "source_location": "L212", "weight": 1.0, "context": "return_type"}, {"source": "auth_authservicetests_authservicetests_logout_with_invalid_token_throws", "target": "fact", "relation": "references", "confidence": "EXTRACTED", "source_file": "backend/tests/ExpenseTracker.UnitTests/Auth/AuthServiceTests.cs", "source_location": "L212", "weight": 1.0, "context": "attribute"}, {"source": "auth_authservicetests_authservicetests_logout_with_invalid_token_throws", "target": "trait", "relation": "references", "confidence": "EXTRACTED", "source_file": "backend/tests/ExpenseTracker.UnitTests/Auth/AuthServiceTests.cs", "source_location": "L212", "weight": 1.0, "context": "attribute"}, {"source": "auth_authservicetests_authservicetests", "target": "auth_authservicetests_authservicetests_getme_returns_user_dto", "relation": "method", "confidence": "EXTRACTED", "source_file": "backend/tests/ExpenseTracker.UnitTests/Auth/AuthServiceTests.cs", "source_location": "L227", "weight": 1.0}, {"source": "auth_authservicetests_authservicetests_getme_returns_user_dto", "target": "task", "relation": "references", "confidence": "EXTRACTED", "source_file": "backend/tests/ExpenseTracker.UnitTests/Auth/AuthServiceTests.cs", "source_location": "L227", "weight": 1.0, "context": "return_type"}, {"source": "auth_authservicetests_authservicetests_getme_returns_user_dto", "target": "fact", "relation": "references", "confidence": "EXTRACTED", "source_file": "backend/tests/ExpenseTracker.UnitTests/Auth/AuthServiceTests.cs", "source_location": "L227", "weight": 1.0, "context": "attribute"}, {"source": "auth_authservicetests_authservicetests_getme_returns_user_dto", "target": "trait", "relation": "references", "confidence": "EXTRACTED", "source_file": "backend/tests/ExpenseTracker.UnitTests/Auth/AuthServiceTests.cs", "source_location": "L227", "weight": 1.0, "context": "attribute"}, {"source": "auth_authservicetests_authservicetests", "target": "auth_authservicetests_authservicetests_getme_with_nonexistent_user_throws_notfound", "relation": "method", "confidence": "EXTRACTED", "source_file": "backend/tests/ExpenseTracker.UnitTests/Auth/AuthServiceTests.cs", "source_location": "L245", "weight": 1.0}, {"source": "auth_authservicetests_authservicetests_getme_with_nonexistent_user_throws_notfound", "target": "task", "relation": "references", "confidence": "EXTRACTED", "source_file": "backend/tests/ExpenseTracker.UnitTests/Auth/AuthServiceTests.cs", "source_location": "L245", "weight": 1.0, "context": "return_type"}, {"source": "auth_authservicetests_authservicetests_getme_with_nonexistent_user_throws_notfound", "target": "fact", "relation": "references", "confidence": "EXTRACTED", "source_file": "backend/tests/ExpenseTracker.UnitTests/Auth/AuthServiceTests.cs", "source_location": "L245", "weight": 1.0, "context": "attribute"}, {"source": "auth_authservicetests_authservicetests_getme_with_nonexistent_user_throws_notfound", "target": "trait", "relation": "references", "confidence": "EXTRACTED", "source_file": "backend/tests/ExpenseTracker.UnitTests/Auth/AuthServiceTests.cs", "source_location": "L245", "weight": 1.0, "context": "attribute"}, {"source": "auth_authservicetests_authservicetests_register_creates_user_and_returns_tokens", "target": "auth_authservicetests_authservicetests_createrefreshtoken", "relation": "calls", "context": "call", "confidence": "EXTRACTED", "source_file": "backend/tests/ExpenseTracker.UnitTests/Auth/AuthServiceTests.cs", "source_location": "L50", "weight": 1.0}, {"source": "auth_authservicetests_authservicetests_login_with_correct_password_returns_tokens", "target": "auth_authservicetests_authservicetests_createrefreshtoken", "relation": "calls", "context": "call", "confidence": "EXTRACTED", "source_file": "backend/tests/ExpenseTracker.UnitTests/Auth/AuthServiceTests.cs", "source_location": "L98", "weight": 1.0}, {"source": "auth_authservicetests_authservicetests_refresh_rotates_token_and_revokes_old", "target": "auth_authservicetests_authservicetests_createrefreshtoken", "relation": "calls", "context": "call", "confidence": "EXTRACTED", "source_file": "backend/tests/ExpenseTracker.UnitTests/Auth/AuthServiceTests.cs", "source_location": "L149", "weight": 1.0}, {"source": "auth_authservicetests_authservicetests_logout_revokes_token", "target": "auth_authservicetests_authservicetests_createrefreshtoken", "relation": "calls", "context": "call", "confidence": "EXTRACTED", "source_file": "backend/tests/ExpenseTracker.UnitTests/Auth/AuthServiceTests.cs", "source_location": "L202", "weight": 1.0}], "raw_calls": [{"caller_nid": "auth_authservicetests_authservicetests_createrefreshtoken", "callee": "AddDays", "is_member_call": true, "source_file": "D:\\JamProject\\ExpenseTracker\\backend\\tests\\ExpenseTracker.UnitTests\\Auth\\AuthServiceTests.cs", "source_location": "L34", "receiver": null}, {"caller_nid": "auth_authservicetests_authservicetests_register_creates_user_and_returns_tokens", "callee": "Returns", "is_member_call": true, "source_file": "D:\\JamProject\\ExpenseTracker\\backend\\tests\\ExpenseTracker.UnitTests\\Auth\\AuthServiceTests.cs", "source_location": "L46", "receiver": null}, {"caller_nid": "auth_authservicetests_authservicetests_register_creates_user_and_returns_tokens", "callee": "ExistsByEmailAsync", "is_member_call": true, "source_file": "D:\\JamProject\\ExpenseTracker\\backend\\tests\\ExpenseTracker.UnitTests\\Auth\\AuthServiceTests.cs", "source_location": "L46", "receiver": null}, {"caller_nid": "auth_authservicetests_authservicetests_register_creates_user_and_returns_tokens", "callee": "Returns", "is_member_call": true, "source_file": "D:\\JamProject\\ExpenseTracker\\backend\\tests\\ExpenseTracker.UnitTests\\Auth\\AuthServiceTests.cs", "source_location": "L47", "receiver": null}, {"caller_nid": "auth_authservicetests_authservicetests_register_creates_user_and_returns_tokens", "callee": "HashPassword", "is_member_call": true, "source_file": "D:\\JamProject\\ExpenseTracker\\backend\\tests\\ExpenseTracker.UnitTests\\Auth\\AuthServiceTests.cs", "source_location": "L47", "receiver": null}, {"caller_nid": "auth_authservicetests_authservicetests_register_creates_user_and_returns_tokens", "callee": "Returns", "is_member_call": true, "source_file": "D:\\JamProject\\ExpenseTracker\\backend\\tests\\ExpenseTracker.UnitTests\\Auth\\AuthServiceTests.cs", "source_location": "L48", "receiver": null}, {"caller_nid": "auth_authservicetests_authservicetests_register_creates_user_and_returns_tokens", "callee": "GenerateToken", "is_member_call": true, "source_file": "D:\\JamProject\\ExpenseTracker\\backend\\tests\\ExpenseTracker.UnitTests\\Auth\\AuthServiceTests.cs", "source_location": "L48", "receiver": null}, {"caller_nid": "auth_authservicetests_authservicetests_register_creates_user_and_returns_tokens", "callee": "Any<Guid>", "is_member_call": true, "source_file": "D:\\JamProject\\ExpenseTracker\\backend\\tests\\ExpenseTracker.UnitTests\\Auth\\AuthServiceTests.cs", "source_location": "L48", "receiver": null}, {"caller_nid": "auth_authservicetests_authservicetests_register_creates_user_and_returns_tokens", "callee": "Returns", "is_member_call": true, "source_file": "D:\\JamProject\\ExpenseTracker\\backend\\tests\\ExpenseTracker.UnitTests\\Auth\\AuthServiceTests.cs", "source_location": "L49", "receiver": null}, {"caller_nid": "auth_authservicetests_authservicetests_register_creates_user_and_returns_tokens", "callee": "GenerateAsync", "is_member_call": true, "source_file": "D:\\JamProject\\ExpenseTracker\\backend\\tests\\ExpenseTracker.UnitTests\\Auth\\AuthServiceTests.cs", "source_location": "L49", "receiver": null}, {"caller_nid": "auth_authservicetests_authservicetests_register_creates_user_and_returns_tokens", "callee": "Any<Guid>", "is_member_call": true, "source_file": "D:\\JamProject\\ExpenseTracker\\backend\\tests\\ExpenseTracker.UnitTests\\Auth\\AuthServiceTests.cs", "source_location": "L49", "receiver": null}, {"caller_nid": "auth_authservicetests_authservicetests_register_creates_user_and_returns_tokens", "callee": "RegisterAsync", "is_member_call": true, "source_file": "D:\\JamProject\\ExpenseTracker\\backend\\tests\\ExpenseTracker.UnitTests\\Auth\\AuthServiceTests.cs", "source_location": "L53", "receiver": null}, {"caller_nid": "auth_authservicetests_authservicetests_register_creates_user_and_returns_tokens", "callee": "NotBeNull", "is_member_call": true, "source_file": "D:\\JamProject\\ExpenseTracker\\backend\\tests\\ExpenseTracker.UnitTests\\Auth\\AuthServiceTests.cs", "source_location": "L56", "receiver": null}, {"caller_nid": "auth_authservicetests_authservicetests_register_creates_user_and_returns_tokens", "callee": "Should", "is_member_call": true, "source_file": "D:\\JamProject\\ExpenseTracker\\backend\\tests\\ExpenseTracker.UnitTests\\Auth\\AuthServiceTests.cs", "source_location": "L56", "receiver": null}, {"caller_nid": "auth_authservicetests_authservicetests_register_creates_user_and_returns_tokens", "callee": "NotBeNull", "is_member_call": true, "source_file": "D:\\JamProject\\ExpenseTracker\\backend\\tests\\ExpenseTracker.UnitTests\\Auth\\AuthServiceTests.cs", "source_location": "L57", "receiver": null}, {"caller_nid": "auth_authservicetests_authservicetests_register_creates_user_and_returns_tokens", "callee": "Should", "is_member_call": true, "source_file": "D:\\JamProject\\ExpenseTracker\\backend\\tests\\ExpenseTracker.UnitTests\\Auth\\AuthServiceTests.cs", "source_location": "L57", "receiver": null}, {"caller_nid": "auth_authservicetests_authservicetests_register_creates_user_and_returns_tokens", "callee": "NotBeNullOrWhiteSpace", "is_member_call": true, "source_file": "D:\\JamProject\\ExpenseTracker\\backend\\tests\\ExpenseTracker.UnitTests\\Auth\\AuthServiceTests.cs", "source_location": "L58", "receiver": null}, {"caller_nid": "auth_authservicetests_authservicetests_register_creates_user_and_returns_tokens", "callee": "Should", "is_member_call": true, "source_file": "D:\\JamProject\\ExpenseTracker\\backend\\tests\\ExpenseTracker.UnitTests\\Auth\\AuthServiceTests.cs", "source_location": "L58", "receiver": null}, {"caller_nid": "auth_authservicetests_authservicetests_register_creates_user_and_returns_tokens", "callee": "Be", "is_member_call": true, "source_file": "D:\\JamProject\\ExpenseTracker\\backend\\tests\\ExpenseTracker.UnitTests\\Auth\\AuthServiceTests.cs", "source_location": "L59", "receiver": null}, {"caller_nid": "auth_authservicetests_authservicetests_register_creates_user_and_returns_tokens", "callee": "Should", "is_member_call": true, "source_file": "D:\\JamProject\\ExpenseTracker\\backend\\tests\\ExpenseTracker.UnitTests\\Auth\\AuthServiceTests.cs", "source_location": "L59", "receiver": null}, {"caller_nid": "auth_authservicetests_authservicetests_register_creates_user_and_returns_tokens", "callee": "NotBeNull", "is_member_call": true, "source_file": "D:\\JamProject\\ExpenseTracker\\backend\\tests\\ExpenseTracker.UnitTests\\Auth\\AuthServiceTests.cs", "source_location": "L60", "receiver": null}, {"caller_nid": "auth_authservicetests_authservicetests_register_creates_user_and_returns_tokens", "callee": "Should", "is_member_call": true, "source_file": "D:\\JamProject\\ExpenseTracker\\backend\\tests\\ExpenseTracker.UnitTests\\Auth\\AuthServiceTests.cs", "source_location": "L60", "receiver": null}, {"caller_nid": "auth_authservicetests_authservicetests_register_creates_user_and_returns_tokens", "callee": "Be", "is_member_call": true, "source_file": "D:\\JamProject\\ExpenseTracker\\backend\\tests\\ExpenseTracker.UnitTests\\Auth\\AuthServiceTests.cs", "source_location": "L61", "receiver": null}, {"caller_nid": "auth_authservicetests_authservicetests_register_creates_user_and_returns_tokens", "callee": "Should", "is_member_call": true, "source_file": "D:\\JamProject\\ExpenseTracker\\backend\\tests\\ExpenseTracker.UnitTests\\Auth\\AuthServiceTests.cs", "source_location": "L61", "receiver": null}, {"caller_nid": "auth_authservicetests_authservicetests_register_creates_user_and_returns_tokens", "callee": "Be", "is_member_call": true, "source_file": "D:\\JamProject\\ExpenseTracker\\backend\\tests\\ExpenseTracker.UnitTests\\Auth\\AuthServiceTests.cs", "source_location": "L62", "receiver": null}, {"caller_nid": "auth_authservicetests_authservicetests_register_creates_user_and_returns_tokens", "callee": "Should", "is_member_call": true, "source_file": "D:\\JamProject\\ExpenseTracker\\backend\\tests\\ExpenseTracker.UnitTests\\Auth\\AuthServiceTests.cs", "source_location": "L62", "receiver": null}, {"caller_nid": "auth_authservicetests_authservicetests_register_creates_user_and_returns_tokens", "callee": "AddAsync", "is_member_call": true, "source_file": "D:\\JamProject\\ExpenseTracker\\backend\\tests\\ExpenseTracker.UnitTests\\Auth\\AuthServiceTests.cs", "source_location": "L64", "receiver": null}, {"caller_nid": "auth_authservicetests_authservicetests_register_creates_user_and_returns_tokens", "callee": "Received", "is_member_call": true, "source_file": "D:\\JamProject\\ExpenseTracker\\backend\\tests\\ExpenseTracker.UnitTests\\Auth\\AuthServiceTests.cs", "source_location": "L64", "receiver": null}, {"caller_nid": "auth_authservicetests_authservicetests_register_creates_user_and_returns_tokens", "callee": "Any<User>", "is_member_call": true, "source_file": "D:\\JamProject\\ExpenseTracker\\backend\\tests\\ExpenseTracker.UnitTests\\Auth\\AuthServiceTests.cs", "source_location": "L64", "receiver": null}, {"caller_nid": "auth_authservicetests_authservicetests_register_creates_user_and_returns_tokens", "callee": "GenerateAsync", "is_member_call": true, "source_file": "D:\\JamProject\\ExpenseTracker\\backend\\tests\\ExpenseTracker.UnitTests\\Auth\\AuthServiceTests.cs", "source_location": "L65", "receiver": null}, {"caller_nid": "auth_authservicetests_authservicetests_register_creates_user_and_returns_tokens", "callee": "Received", "is_member_call": true, "source_file": "D:\\JamProject\\ExpenseTracker\\backend\\tests\\ExpenseTracker.UnitTests\\Auth\\AuthServiceTests.cs", "source_location": "L65", "receiver": null}, {"caller_nid": "auth_authservicetests_authservicetests_register_creates_user_and_returns_tokens", "callee": "Any<Guid>", "is_member_call": true, "source_file": "D:\\JamProject\\ExpenseTracker\\backend\\tests\\ExpenseTracker.UnitTests\\Auth\\AuthServiceTests.cs", "source_location": "L65", "receiver": null}, {"caller_nid": "auth_authservicetests_authservicetests_register_rejects_duplicate_email", "callee": "Returns", "is_member_call": true, "source_file": "D:\\JamProject\\ExpenseTracker\\backend\\tests\\ExpenseTracker.UnitTests\\Auth\\AuthServiceTests.cs", "source_location": "L74", "receiver": null}, {"caller_nid": "auth_authservicetests_authservicetests_register_rejects_duplicate_email", "callee": "ExistsByEmailAsync", "is_member_call": true, "source_file": "D:\\JamProject\\ExpenseTracker\\backend\\tests\\ExpenseTracker.UnitTests\\Auth\\AuthServiceTests.cs", "source_location": "L74", "receiver": null}, {"caller_nid": "auth_authservicetests_authservicetests_register_rejects_duplicate_email", "callee": "WithMessage", "is_member_call": true, "source_file": "D:\\JamProject\\ExpenseTracker\\backend\\tests\\ExpenseTracker.UnitTests\\Auth\\AuthServiceTests.cs", "source_location": "L77", "receiver": null}, {"caller_nid": "auth_authservicetests_authservicetests_register_rejects_duplicate_email", "callee": "ThrowAsync<DomainValidationException>", "is_member_call": true, "source_file": "D:\\JamProject\\ExpenseTracker\\backend\\tests\\ExpenseTracker.UnitTests\\Auth\\AuthServiceTests.cs", "source_location": "L77", "receiver": null}, {"caller_nid": "auth_authservicetests_authservicetests_register_rejects_duplicate_email", "callee": "Should", "is_member_call": true, "source_file": "D:\\JamProject\\ExpenseTracker\\backend\\tests\\ExpenseTracker.UnitTests\\Auth\\AuthServiceTests.cs", "source_location": "L77", "receiver": null}, {"caller_nid": "auth_authservicetests_authservicetests_register_rejects_duplicate_email", "callee": "Invoking", "is_member_call": true, "source_file": "D:\\JamProject\\ExpenseTracker\\backend\\tests\\ExpenseTracker.UnitTests\\Auth\\AuthServiceTests.cs", "source_location": "L77", "receiver": null}, {"caller_nid": "auth_authservicetests_authservicetests_register_rejects_duplicate_email", "callee": "RegisterAsync", "is_member_call": true, "source_file": "D:\\JamProject\\ExpenseTracker\\backend\\tests\\ExpenseTracker.UnitTests\\Auth\\AuthServiceTests.cs", "source_location": "L77", "receiver": null}, {"caller_nid": "auth_authservicetests_authservicetests_register_rejects_duplicate_email", "callee": "AddAsync", "is_member_call": true, "source_file": "D:\\JamProject\\ExpenseTracker\\backend\\tests\\ExpenseTracker.UnitTests\\Auth\\AuthServiceTests.cs", "source_location": "L81", "receiver": null}, {"caller_nid": "auth_authservicetests_authservicetests_register_rejects_duplicate_email", "callee": "DidNotReceive", "is_member_call": true, "source_file": "D:\\JamProject\\ExpenseTracker\\backend\\tests\\ExpenseTracker.UnitTests\\Auth\\AuthServiceTests.cs", "source_location": "L81", "receiver": null}, {"caller_nid": "auth_authservicetests_authservicetests_register_rejects_duplicate_email", "callee": "Any<User>", "is_member_call": true, "source_file": "D:\\JamProject\\ExpenseTracker\\backend\\tests\\ExpenseTracker.UnitTests\\Auth\\AuthServiceTests.cs", "source_location": "L81", "receiver": null}, {"caller_nid": "auth_authservicetests_authservicetests_login_with_correct_password_returns_tokens", "callee": "Returns", "is_member_call": true, "source_file": "D:\\JamProject\\ExpenseTracker\\backend\\tests\\ExpenseTracker.UnitTests\\Auth\\AuthServiceTests.cs", "source_location": "L94", "receiver": null}, {"caller_nid": "auth_authservicetests_authservicetests_login_with_correct_password_returns_tokens", "callee": "FindByEmailAsync", "is_member_call": true, "source_file": "D:\\JamProject\\ExpenseTracker\\backend\\tests\\ExpenseTracker.UnitTests\\Auth\\AuthServiceTests.cs", "source_location": "L94", "receiver": null}, {"caller_nid": "auth_authservicetests_authservicetests_login_with_correct_password_returns_tokens", "callee": "Returns", "is_member_call": true, "source_file": "D:\\JamProject\\ExpenseTracker\\backend\\tests\\ExpenseTracker.UnitTests\\Auth\\AuthServiceTests.cs", "source_location": "L95", "receiver": null}, {"caller_nid": "auth_authservicetests_authservicetests_login_with_correct_password_returns_tokens", "callee": "VerifyPassword", "is_member_call": true, "source_file": "D:\\JamProject\\ExpenseTracker\\backend\\tests\\ExpenseTracker.UnitTests\\Auth\\AuthServiceTests.cs", "source_location": "L95", "receiver": null}, {"caller_nid": "auth_authservicetests_authservicetests_login_with_correct_password_returns_tokens", "callee": "Returns", "is_member_call": true, "source_file": "D:\\JamProject\\ExpenseTracker\\backend\\tests\\ExpenseTracker.UnitTests\\Auth\\AuthServiceTests.cs", "source_location": "L96", "receiver": null}, {"caller_nid": "auth_authservicetests_authservicetests_login_with_correct_password_returns_tokens", "callee": "GenerateToken", "is_member_call": true, "source_file": "D:\\JamProject\\ExpenseTracker\\backend\\tests\\ExpenseTracker.UnitTests\\Auth\\AuthServiceTests.cs", "source_location": "L96", "receiver": null}, {"caller_nid": "auth_authservicetests_authservicetests_login_with_correct_password_returns_tokens", "callee": "Returns", "is_member_call": true, "source_file": "D:\\JamProject\\ExpenseTracker\\backend\\tests\\ExpenseTracker.UnitTests\\Auth\\AuthServiceTests.cs", "source_location": "L97", "receiver": null}, {"caller_nid": "auth_authservicetests_authservicetests_login_with_correct_password_returns_tokens", "callee": "GenerateAsync", "is_member_call": true, "source_file": "D:\\JamProject\\ExpenseTracker\\backend\\tests\\ExpenseTracker.UnitTests\\Auth\\AuthServiceTests.cs", "source_location": "L97", "receiver": null}, {"caller_nid": "auth_authservicetests_authservicetests_login_with_correct_password_returns_tokens", "callee": "LoginAsync", "is_member_call": true, "source_file": "D:\\JamProject\\ExpenseTracker\\backend\\tests\\ExpenseTracker.UnitTests\\Auth\\AuthServiceTests.cs", "source_location": "L101", "receiver": null}, {"caller_nid": "auth_authservicetests_authservicetests_login_with_correct_password_returns_tokens", "callee": "NotBeNull", "is_member_call": true, "source_file": "D:\\JamProject\\ExpenseTracker\\backend\\tests\\ExpenseTracker.UnitTests\\Auth\\AuthServiceTests.cs", "source_location": "L104", "receiver": null}, {"caller_nid": "auth_authservicetests_authservicetests_login_with_correct_password_returns_tokens", "callee": "Should", "is_member_call": true, "source_file": "D:\\JamProject\\ExpenseTracker\\backend\\tests\\ExpenseTracker.UnitTests\\Auth\\AuthServiceTests.cs", "source_location": "L104", "receiver": null}, {"caller_nid": "auth_authservicetests_authservicetests_login_with_correct_password_returns_tokens", "callee": "NotBeNull", "is_member_call": true, "source_file": "D:\\JamProject\\ExpenseTracker\\backend\\tests\\ExpenseTracker.UnitTests\\Auth\\AuthServiceTests.cs", "source_location": "L105", "receiver": null}, {"caller_nid": "auth_authservicetests_authservicetests_login_with_correct_password_returns_tokens", "callee": "Should", "is_member_call": true, "source_file": "D:\\JamProject\\ExpenseTracker\\backend\\tests\\ExpenseTracker.UnitTests\\Auth\\AuthServiceTests.cs", "source_location": "L105", "receiver": null}, {"caller_nid": "auth_authservicetests_authservicetests_login_with_correct_password_returns_tokens", "callee": "NotBeNullOrWhiteSpace", "is_member_call": true, "source_file": "D:\\JamProject\\ExpenseTracker\\backend\\tests\\ExpenseTracker.UnitTests\\Auth\\AuthServiceTests.cs", "source_location": "L106", "receiver": null}, {"caller_nid": "auth_authservicetests_authservicetests_login_with_correct_password_returns_tokens", "callee": "Should", "is_member_call": true, "source_file": "D:\\JamProject\\ExpenseTracker\\backend\\tests\\ExpenseTracker.UnitTests\\Auth\\AuthServiceTests.cs", "source_location": "L106", "receiver": null}, {"caller_nid": "auth_authservicetests_authservicetests_login_with_correct_password_returns_tokens", "callee": "Be", "is_member_call": true, "source_file": "D:\\JamProject\\ExpenseTracker\\backend\\tests\\ExpenseTracker.UnitTests\\Auth\\AuthServiceTests.cs", "source_location": "L107", "receiver": null}, {"caller_nid": "auth_authservicetests_authservicetests_login_with_correct_password_returns_tokens", "callee": "Should", "is_member_call": true, "source_file": "D:\\JamProject\\ExpenseTracker\\backend\\tests\\ExpenseTracker.UnitTests\\Auth\\AuthServiceTests.cs", "source_location": "L107", "receiver": null}, {"caller_nid": "auth_authservicetests_authservicetests_login_with_wrong_password_throws_invalidcredentials", "callee": "Returns", "is_member_call": true, "source_file": "D:\\JamProject\\ExpenseTracker\\backend\\tests\\ExpenseTracker.UnitTests\\Auth\\AuthServiceTests.cs", "source_location": "L118", "receiver": null}, {"caller_nid": "auth_authservicetests_authservicetests_login_with_wrong_password_throws_invalidcredentials", "callee": "FindByEmailAsync", "is_member_call": true, "source_file": "D:\\JamProject\\ExpenseTracker\\backend\\tests\\ExpenseTracker.UnitTests\\Auth\\AuthServiceTests.cs", "source_location": "L118", "receiver": null}, {"caller_nid": "auth_authservicetests_authservicetests_login_with_wrong_password_throws_invalidcredentials", "callee": "Returns", "is_member_call": true, "source_file": "D:\\JamProject\\ExpenseTracker\\backend\\tests\\ExpenseTracker.UnitTests\\Auth\\AuthServiceTests.cs", "source_location": "L119", "receiver": null}, {"caller_nid": "auth_authservicetests_authservicetests_login_with_wrong_password_throws_invalidcredentials", "callee": "VerifyPassword", "is_member_call": true, "source_file": "D:\\JamProject\\ExpenseTracker\\backend\\tests\\ExpenseTracker.UnitTests\\Auth\\AuthServiceTests.cs", "source_location": "L119", "receiver": null}, {"caller_nid": "auth_authservicetests_authservicetests_login_with_wrong_password_throws_invalidcredentials", "callee": "WithMessage", "is_member_call": true, "source_file": "D:\\JamProject\\ExpenseTracker\\backend\\tests\\ExpenseTracker.UnitTests\\Auth\\AuthServiceTests.cs", "source_location": "L122", "receiver": null}, {"caller_nid": "auth_authservicetests_authservicetests_login_with_wrong_password_throws_invalidcredentials", "callee": "ThrowAsync<DomainValidationException>", "is_member_call": true, "source_file": "D:\\JamProject\\ExpenseTracker\\backend\\tests\\ExpenseTracker.UnitTests\\Auth\\AuthServiceTests.cs", "source_location": "L122", "receiver": null}, {"caller_nid": "auth_authservicetests_authservicetests_login_with_wrong_password_throws_invalidcredentials", "callee": "Should", "is_member_call": true, "source_file": "D:\\JamProject\\ExpenseTracker\\backend\\tests\\ExpenseTracker.UnitTests\\Auth\\AuthServiceTests.cs", "source_location": "L122", "receiver": null}, {"caller_nid": "auth_authservicetests_authservicetests_login_with_wrong_password_throws_invalidcredentials", "callee": "Invoking", "is_member_call": true, "source_file": "D:\\JamProject\\ExpenseTracker\\backend\\tests\\ExpenseTracker.UnitTests\\Auth\\AuthServiceTests.cs", "source_location": "L122", "receiver": null}, {"caller_nid": "auth_authservicetests_authservicetests_login_with_wrong_password_throws_invalidcredentials", "callee": "LoginAsync", "is_member_call": true, "source_file": "D:\\JamProject\\ExpenseTracker\\backend\\tests\\ExpenseTracker.UnitTests\\Auth\\AuthServiceTests.cs", "source_location": "L122", "receiver": null}, {"caller_nid": "auth_authservicetests_authservicetests_login_with_nonexistent_email_throws_invalidcredentials", "callee": "Returns", "is_member_call": true, "source_file": "D:\\JamProject\\ExpenseTracker\\backend\\tests\\ExpenseTracker.UnitTests\\Auth\\AuthServiceTests.cs", "source_location": "L133", "receiver": null}, {"caller_nid": "auth_authservicetests_authservicetests_login_with_nonexistent_email_throws_invalidcredentials", "callee": "FindByEmailAsync", "is_member_call": true, "source_file": "D:\\JamProject\\ExpenseTracker\\backend\\tests\\ExpenseTracker.UnitTests\\Auth\\AuthServiceTests.cs", "source_location": "L133", "receiver": null}, {"caller_nid": "auth_authservicetests_authservicetests_login_with_nonexistent_email_throws_invalidcredentials", "callee": "WithMessage", "is_member_call": true, "source_file": "D:\\JamProject\\ExpenseTracker\\backend\\tests\\ExpenseTracker.UnitTests\\Auth\\AuthServiceTests.cs", "source_location": "L136", "receiver": null}, {"caller_nid": "auth_authservicetests_authservicetests_login_with_nonexistent_email_throws_invalidcredentials", "callee": "ThrowAsync<DomainValidationException>", "is_member_call": true, "source_file": "D:\\JamProject\\ExpenseTracker\\backend\\tests\\ExpenseTracker.UnitTests\\Auth\\AuthServiceTests.cs", "source_location": "L136", "receiver": null}, {"caller_nid": "auth_authservicetests_authservicetests_login_with_nonexistent_email_throws_invalidcredentials", "callee": "Should", "is_member_call": true, "source_file": "D:\\JamProject\\ExpenseTracker\\backend\\tests\\ExpenseTracker.UnitTests\\Auth\\AuthServiceTests.cs", "source_location": "L136", "receiver": null}, {"caller_nid": "auth_authservicetests_authservicetests_login_with_nonexistent_email_throws_invalidcredentials", "callee": "Invoking", "is_member_call": true, "source_file": "D:\\JamProject\\ExpenseTracker\\backend\\tests\\ExpenseTracker.UnitTests\\Auth\\AuthServiceTests.cs", "source_location": "L136", "receiver": null}, {"caller_nid": "auth_authservicetests_authservicetests_login_with_nonexistent_email_throws_invalidcredentials", "callee": "LoginAsync", "is_member_call": true, "source_file": "D:\\JamProject\\ExpenseTracker\\backend\\tests\\ExpenseTracker.UnitTests\\Auth\\AuthServiceTests.cs", "source_location": "L136", "receiver": null}, {"caller_nid": "auth_authservicetests_authservicetests_refresh_rotates_token_and_revokes_old", "callee": "Returns", "is_member_call": true, "source_file": "D:\\JamProject\\ExpenseTracker\\backend\\tests\\ExpenseTracker.UnitTests\\Auth\\AuthServiceTests.cs", "source_location": "L151", "receiver": null}, {"caller_nid": "auth_authservicetests_authservicetests_refresh_rotates_token_and_revokes_old", "callee": "ValidateAsync", "is_member_call": true, "source_file": "D:\\JamProject\\ExpenseTracker\\backend\\tests\\ExpenseTracker.UnitTests\\Auth\\AuthServiceTests.cs", "source_location": "L151", "receiver": null}, {"caller_nid": "auth_authservicetests_authservicetests_refresh_rotates_token_and_revokes_old", "callee": "Returns", "is_member_call": true, "source_file": "D:\\JamProject\\ExpenseTracker\\backend\\tests\\ExpenseTracker.UnitTests\\Auth\\AuthServiceTests.cs", "source_location": "L152", "receiver": null}, {"caller_nid": "auth_authservicetests_authservicetests_refresh_rotates_token_and_revokes_old", "callee": "RotateAsync", "is_member_call": true, "source_file": "D:\\JamProject\\ExpenseTracker\\backend\\tests\\ExpenseTracker.UnitTests\\Auth\\AuthServiceTests.cs", "source_location": "L152", "receiver": null}, {"caller_nid": "auth_authservicetests_authservicetests_refresh_rotates_token_and_revokes_old", "callee": "Returns", "is_member_call": true, "source_file": "D:\\JamProject\\ExpenseTracker\\backend\\tests\\ExpenseTracker.UnitTests\\Auth\\AuthServiceTests.cs", "source_location": "L154", "receiver": null}, {"caller_nid": "auth_authservicetests_authservicetests_refresh_rotates_token_and_revokes_old", "callee": "FindByIdAsync", "is_member_call": true, "source_file": "D:\\JamProject\\ExpenseTracker\\backend\\tests\\ExpenseTracker.UnitTests\\Auth\\AuthServiceTests.cs", "source_location": "L154", "receiver": null}, {"caller_nid": "auth_authservicetests_authservicetests_refresh_rotates_token_and_revokes_old", "callee": "Returns", "is_member_call": true, "source_file": "D:\\JamProject\\ExpenseTracker\\backend\\tests\\ExpenseTracker.UnitTests\\Auth\\AuthServiceTests.cs", "source_location": "L155", "receiver": null}, {"caller_nid": "auth_authservicetests_authservicetests_refresh_rotates_token_and_revokes_old", "callee": "GenerateToken", "is_member_call": true, "source_file": "D:\\JamProject\\ExpenseTracker\\backend\\tests\\ExpenseTracker.UnitTests\\Auth\\AuthServiceTests.cs", "source_location": "L155", "receiver": null}, {"caller_nid": "auth_authservicetests_authservicetests_refresh_rotates_token_and_revokes_old", "callee": "RefreshAsync", "is_member_call": true, "source_file": "D:\\JamProject\\ExpenseTracker\\backend\\tests\\ExpenseTracker.UnitTests\\Auth\\AuthServiceTests.cs", "source_location": "L158", "receiver": null}, {"caller_nid": "auth_authservicetests_authservicetests_refresh_rotates_token_and_revokes_old", "callee": "NotBeNull", "is_member_call": true, "source_file": "D:\\JamProject\\ExpenseTracker\\backend\\tests\\ExpenseTracker.UnitTests\\Auth\\AuthServiceTests.cs", "source_location": "L161", "receiver": null}, {"caller_nid": "auth_authservicetests_authservicetests_refresh_rotates_token_and_revokes_old", "callee": "Should", "is_member_call": true, "source_file": "D:\\JamProject\\ExpenseTracker\\backend\\tests\\ExpenseTracker.UnitTests\\Auth\\AuthServiceTests.cs", "source_location": "L161", "receiver": null}, {"caller_nid": "auth_authservicetests_authservicetests_refresh_rotates_token_and_revokes_old", "callee": "NotBeNull", "is_member_call": true, "source_file": "D:\\JamProject\\ExpenseTracker\\backend\\tests\\ExpenseTracker.UnitTests\\Auth\\AuthServiceTests.cs", "source_location": "L162", "receiver": null}, {"caller_nid": "auth_authservicetests_authservicetests_refresh_rotates_token_and_revokes_old", "callee": "Should", "is_member_call": true, "source_file": "D:\\JamProject\\ExpenseTracker\\backend\\tests\\ExpenseTracker.UnitTests\\Auth\\AuthServiceTests.cs", "source_location": "L162", "receiver": null}, {"caller_nid": "auth_authservicetests_authservicetests_refresh_rotates_token_and_revokes_old", "callee": "NotBeNullOrWhiteSpace", "is_member_call": true, "source_file": "D:\\JamProject\\ExpenseTracker\\backend\\tests\\ExpenseTracker.UnitTests\\Auth\\AuthServiceTests.cs", "source_location": "L163", "receiver": null}, {"caller_nid": "auth_authservicetests_authservicetests_refresh_rotates_token_and_revokes_old", "callee": "Should", "is_member_call": true, "source_file": "D:\\JamProject\\ExpenseTracker\\backend\\tests\\ExpenseTracker.UnitTests\\Auth\\AuthServiceTests.cs", "source_location": "L163", "receiver": null}, {"caller_nid": "auth_authservicetests_authservicetests_refresh_rotates_token_and_revokes_old", "callee": "RotateAsync", "is_member_call": true, "source_file": "D:\\JamProject\\ExpenseTracker\\backend\\tests\\ExpenseTracker.UnitTests\\Auth\\AuthServiceTests.cs", "source_location": "L164", "receiver": null}, {"caller_nid": "auth_authservicetests_authservicetests_refresh_rotates_token_and_revokes_old", "callee": "Received", "is_member_call": true, "source_file": "D:\\JamProject\\ExpenseTracker\\backend\\tests\\ExpenseTracker.UnitTests\\Auth\\AuthServiceTests.cs", "source_location": "L164", "receiver": null}, {"caller_nid": "auth_authservicetests_authservicetests_refresh_with_revoked_token_throws", "callee": "ThrowsAsync", "is_member_call": true, "source_file": "D:\\JamProject\\ExpenseTracker\\backend\\tests\\ExpenseTracker.UnitTests\\Auth\\AuthServiceTests.cs", "source_location": "L172", "receiver": null}, {"caller_nid": "auth_authservicetests_authservicetests_refresh_with_revoked_token_throws", "callee": "ValidateAsync", "is_member_call": true, "source_file": "D:\\JamProject\\ExpenseTracker\\backend\\tests\\ExpenseTracker.UnitTests\\Auth\\AuthServiceTests.cs", "source_location": "L172", "receiver": null}, {"caller_nid": "auth_authservicetests_authservicetests_refresh_with_revoked_token_throws", "callee": "WithMessage", "is_member_call": true, "source_file": "D:\\JamProject\\ExpenseTracker\\backend\\tests\\ExpenseTracker.UnitTests\\Auth\\AuthServiceTests.cs", "source_location": "L176", "receiver": null}, {"caller_nid": "auth_authservicetests_authservicetests_refresh_with_revoked_token_throws", "callee": "ThrowAsync<RefreshTokenValidationException>", "is_member_call": true, "source_file": "D:\\JamProject\\ExpenseTracker\\backend\\tests\\ExpenseTracker.UnitTests\\Auth\\AuthServiceTests.cs", "source_location": "L176", "receiver": null}, {"caller_nid": "auth_authservicetests_authservicetests_refresh_with_revoked_token_throws", "callee": "Should", "is_member_call": true, "source_file": "D:\\JamProject\\ExpenseTracker\\backend\\tests\\ExpenseTracker.UnitTests\\Auth\\AuthServiceTests.cs", "source_location": "L176", "receiver": null}, {"caller_nid": "auth_authservicetests_authservicetests_refresh_with_revoked_token_throws", "callee": "Invoking", "is_member_call": true, "source_file": "D:\\JamProject\\ExpenseTracker\\backend\\tests\\ExpenseTracker.UnitTests\\Auth\\AuthServiceTests.cs", "source_location": "L176", "receiver": null}, {"caller_nid": "auth_authservicetests_authservicetests_refresh_with_revoked_token_throws", "callee": "RefreshAsync", "is_member_call": true, "source_file": "D:\\JamProject\\ExpenseTracker\\backend\\tests\\ExpenseTracker.UnitTests\\Auth\\AuthServiceTests.cs", "source_location": "L176", "receiver": null}, {"caller_nid": "auth_authservicetests_authservicetests_refresh_with_expired_token_throws", "callee": "ThrowsAsync", "is_member_call": true, "source_file": "D:\\JamProject\\ExpenseTracker\\backend\\tests\\ExpenseTracker.UnitTests\\Auth\\AuthServiceTests.cs", "source_location": "L186", "receiver": null}, {"caller_nid": "auth_authservicetests_authservicetests_refresh_with_expired_token_throws", "callee": "ValidateAsync", "is_member_call": true, "source_file": "D:\\JamProject\\ExpenseTracker\\backend\\tests\\ExpenseTracker.UnitTests\\Auth\\AuthServiceTests.cs", "source_location": "L186", "receiver": null}, {"caller_nid": "auth_authservicetests_authservicetests_refresh_with_expired_token_throws", "callee": "WithMessage", "is_member_call": true, "source_file": "D:\\JamProject\\ExpenseTracker\\backend\\tests\\ExpenseTracker.UnitTests\\Auth\\AuthServiceTests.cs", "source_location": "L190", "receiver": null}, {"caller_nid": "auth_authservicetests_authservicetests_refresh_with_expired_token_throws", "callee": "ThrowAsync<RefreshTokenValidationException>", "is_member_call": true, "source_file": "D:\\JamProject\\ExpenseTracker\\backend\\tests\\ExpenseTracker.UnitTests\\Auth\\AuthServiceTests.cs", "source_location": "L190", "receiver": null}, {"caller_nid": "auth_authservicetests_authservicetests_refresh_with_expired_token_throws", "callee": "Should", "is_member_call": true, "source_file": "D:\\JamProject\\ExpenseTracker\\backend\\tests\\ExpenseTracker.UnitTests\\Auth\\AuthServiceTests.cs", "source_location": "L190", "receiver": null}, {"caller_nid": "auth_authservicetests_authservicetests_refresh_with_expired_token_throws", "callee": "Invoking", "is_member_call": true, "source_file": "D:\\JamProject\\ExpenseTracker\\backend\\tests\\ExpenseTracker.UnitTests\\Auth\\AuthServiceTests.cs", "source_location": "L190", "receiver": null}, {"caller_nid": "auth_authservicetests_authservicetests_refresh_with_expired_token_throws", "callee": "RefreshAsync", "is_member_call": true, "source_file": "D:\\JamProject\\ExpenseTracker\\backend\\tests\\ExpenseTracker.UnitTests\\Auth\\AuthServiceTests.cs", "source_location": "L190", "receiver": null}, {"caller_nid": "auth_authservicetests_authservicetests_logout_revokes_token", "callee": "Returns", "is_member_call": true, "source_file": "D:\\JamProject\\ExpenseTracker\\backend\\tests\\ExpenseTracker.UnitTests\\Auth\\AuthServiceTests.cs", "source_location": "L203", "receiver": null}, {"caller_nid": "auth_authservicetests_authservicetests_logout_revokes_token", "callee": "ValidateAsync", "is_member_call": true, "source_file": "D:\\JamProject\\ExpenseTracker\\backend\\tests\\ExpenseTracker.UnitTests\\Auth\\AuthServiceTests.cs", "source_location": "L203", "receiver": null}, {"caller_nid": "auth_authservicetests_authservicetests_logout_revokes_token", "callee": "LogoutAsync", "is_member_call": true, "source_file": "D:\\JamProject\\ExpenseTracker\\backend\\tests\\ExpenseTracker.UnitTests\\Auth\\AuthServiceTests.cs", "source_location": "L206", "receiver": null}, {"caller_nid": "auth_authservicetests_authservicetests_logout_revokes_token", "callee": "RevokeAsync", "is_member_call": true, "source_file": "D:\\JamProject\\ExpenseTracker\\backend\\tests\\ExpenseTracker.UnitTests\\Auth\\AuthServiceTests.cs", "source_location": "L209", "receiver": null}, {"caller_nid": "auth_authservicetests_authservicetests_logout_revokes_token", "callee": "Received", "is_member_call": true, "source_file": "D:\\JamProject\\ExpenseTracker\\backend\\tests\\ExpenseTracker.UnitTests\\Auth\\AuthServiceTests.cs", "source_location": "L209", "receiver": null}, {"caller_nid": "auth_authservicetests_authservicetests_logout_with_invalid_token_throws", "callee": "ThrowsAsync", "is_member_call": true, "source_file": "D:\\JamProject\\ExpenseTracker\\backend\\tests\\ExpenseTracker.UnitTests\\Auth\\AuthServiceTests.cs", "source_location": "L217", "receiver": null}, {"caller_nid": "auth_authservicetests_authservicetests_logout_with_invalid_token_throws", "callee": "ValidateAsync", "is_member_call": true, "source_file": "D:\\JamProject\\ExpenseTracker\\backend\\tests\\ExpenseTracker.UnitTests\\Auth\\AuthServiceTests.cs", "source_location": "L217", "receiver": null}, {"caller_nid": "auth_authservicetests_authservicetests_logout_with_invalid_token_throws", "callee": "ThrowAsync<RefreshTokenValidationException>", "is_member_call": true, "source_file": "D:\\JamProject\\ExpenseTracker\\backend\\tests\\ExpenseTracker.UnitTests\\Auth\\AuthServiceTests.cs", "source_location": "L221", "receiver": null}, {"caller_nid": "auth_authservicetests_authservicetests_logout_with_invalid_token_throws", "callee": "Should", "is_member_call": true, "source_file": "D:\\JamProject\\ExpenseTracker\\backend\\tests\\ExpenseTracker.UnitTests\\Auth\\AuthServiceTests.cs", "source_location": "L221", "receiver": null}, {"caller_nid": "auth_authservicetests_authservicetests_logout_with_invalid_token_throws", "callee": "Invoking", "is_member_call": true, "source_file": "D:\\JamProject\\ExpenseTracker\\backend\\tests\\ExpenseTracker.UnitTests\\Auth\\AuthServiceTests.cs", "source_location": "L221", "receiver": null}, {"caller_nid": "auth_authservicetests_authservicetests_logout_with_invalid_token_throws", "callee": "LogoutAsync", "is_member_call": true, "source_file": "D:\\JamProject\\ExpenseTracker\\backend\\tests\\ExpenseTracker.UnitTests\\Auth\\AuthServiceTests.cs", "source_location": "L221", "receiver": null}, {"caller_nid": "auth_authservicetests_authservicetests_getme_returns_user_dto", "callee": "Returns", "is_member_call": true, "source_file": "D:\\JamProject\\ExpenseTracker\\backend\\tests\\ExpenseTracker.UnitTests\\Auth\\AuthServiceTests.cs", "source_location": "L233", "receiver": null}, {"caller_nid": "auth_authservicetests_authservicetests_getme_returns_user_dto", "callee": "FindByIdAsync", "is_member_call": true, "source_file": "D:\\JamProject\\ExpenseTracker\\backend\\tests\\ExpenseTracker.UnitTests\\Auth\\AuthServiceTests.cs", "source_location": "L233", "receiver": null}, {"caller_nid": "auth_authservicetests_authservicetests_getme_returns_user_dto", "callee": "GetMeAsync", "is_member_call": true, "source_file": "D:\\JamProject\\ExpenseTracker\\backend\\tests\\ExpenseTracker.UnitTests\\Auth\\AuthServiceTests.cs", "source_location": "L236", "receiver": null}, {"caller_nid": "auth_authservicetests_authservicetests_getme_returns_user_dto", "callee": "NotBeNull", "is_member_call": true, "source_file": "D:\\JamProject\\ExpenseTracker\\backend\\tests\\ExpenseTracker.UnitTests\\Auth\\AuthServiceTests.cs", "source_location": "L239", "receiver": null}, {"caller_nid": "auth_authservicetests_authservicetests_getme_returns_user_dto", "callee": "Should", "is_member_call": true, "source_file": "D:\\JamProject\\ExpenseTracker\\backend\\tests\\ExpenseTracker.UnitTests\\Auth\\AuthServiceTests.cs", "source_location": "L239", "receiver": null}, {"caller_nid": "auth_authservicetests_authservicetests_getme_returns_user_dto", "callee": "Be", "is_member_call": true, "source_file": "D:\\JamProject\\ExpenseTracker\\backend\\tests\\ExpenseTracker.UnitTests\\Auth\\AuthServiceTests.cs", "source_location": "L240", "receiver": null}, {"caller_nid": "auth_authservicetests_authservicetests_getme_returns_user_dto", "callee": "Should", "is_member_call": true, "source_file": "D:\\JamProject\\ExpenseTracker\\backend\\tests\\ExpenseTracker.UnitTests\\Auth\\AuthServiceTests.cs", "source_location": "L240", "receiver": null}, {"caller_nid": "auth_authservicetests_authservicetests_getme_returns_user_dto", "callee": "Be", "is_member_call": true, "source_file": "D:\\JamProject\\ExpenseTracker\\backend\\tests\\ExpenseTracker.UnitTests\\Auth\\AuthServiceTests.cs", "source_location": "L241", "receiver": null}, {"caller_nid": "auth_authservicetests_authservicetests_getme_returns_user_dto", "callee": "Should", "is_member_call": true, "source_file": "D:\\JamProject\\ExpenseTracker\\backend\\tests\\ExpenseTracker.UnitTests\\Auth\\AuthServiceTests.cs", "source_location": "L241", "receiver": null}, {"caller_nid": "auth_authservicetests_authservicetests_getme_returns_user_dto", "callee": "Be", "is_member_call": true, "source_file": "D:\\JamProject\\ExpenseTracker\\backend\\tests\\ExpenseTracker.UnitTests\\Auth\\AuthServiceTests.cs", "source_location": "L242", "receiver": null}, {"caller_nid": "auth_authservicetests_authservicetests_getme_returns_user_dto", "callee": "Should", "is_member_call": true, "source_file": "D:\\JamProject\\ExpenseTracker\\backend\\tests\\ExpenseTracker.UnitTests\\Auth\\AuthServiceTests.cs", "source_location": "L242", "receiver": null}, {"caller_nid": "auth_authservicetests_authservicetests_getme_with_nonexistent_user_throws_notfound", "callee": "NewGuid", "is_member_call": true, "source_file": "D:\\JamProject\\ExpenseTracker\\backend\\tests\\ExpenseTracker.UnitTests\\Auth\\AuthServiceTests.cs", "source_location": "L250", "receiver": null}, {"caller_nid": "auth_authservicetests_authservicetests_getme_with_nonexistent_user_throws_notfound", "callee": "Returns", "is_member_call": true, "source_file": "D:\\JamProject\\ExpenseTracker\\backend\\tests\\ExpenseTracker.UnitTests\\Auth\\AuthServiceTests.cs", "source_location": "L251", "receiver": null}, {"caller_nid": "auth_authservicetests_authservicetests_getme_with_nonexistent_user_throws_notfound", "callee": "FindByIdAsync", "is_member_call": true, "source_file": "D:\\JamProject\\ExpenseTracker\\backend\\tests\\ExpenseTracker.UnitTests\\Auth\\AuthServiceTests.cs", "source_location": "L251", "receiver": null}, {"caller_nid": "auth_authservicetests_authservicetests_getme_with_nonexistent_user_throws_notfound", "callee": "ThrowAsync<NotFoundException>", "is_member_call": true, "source_file": "D:\\JamProject\\ExpenseTracker\\backend\\tests\\ExpenseTracker.UnitTests\\Auth\\AuthServiceTests.cs", "source_location": "L254", "receiver": null}, {"caller_nid": "auth_authservicetests_authservicetests_getme_with_nonexistent_user_throws_notfound", "callee": "Should", "is_member_call": true, "source_file": "D:\\JamProject\\ExpenseTracker\\backend\\tests\\ExpenseTracker.UnitTests\\Auth\\AuthServiceTests.cs", "source_location": "L254", "receiver": null}, {"caller_nid": "auth_authservicetests_authservicetests_getme_with_nonexistent_user_throws_notfound", "callee": "Invoking", "is_member_call": true, "source_file": "D:\\JamProject\\ExpenseTracker\\backend\\tests\\ExpenseTracker.UnitTests\\Auth\\AuthServiceTests.cs", "source_location": "L254", "receiver": null}, {"caller_nid": "auth_authservicetests_authservicetests_getme_with_nonexistent_user_throws_notfound", "callee": "GetMeAsync", "is_member_call": true, "source_file": "D:\\JamProject\\ExpenseTracker\\backend\\tests\\ExpenseTracker.UnitTests\\Auth\\AuthServiceTests.cs", "source_location": "L254", "receiver": null}]}